Metadata-Version: 2.1
Name: odoo12-addon-shopinvader-guest-mode
Version: 12.0.2.0.0
Summary: Guest mode for Shopinvader
Home-page: https://github.com/shopinvader/odoo-shopinvader
Author: ACSONE SA/NV,Odoo Community Association (OCA)
Author-email: support@odoo-community.org
License: AGPL-3
Platform: UNKNOWN
Classifier: Programming Language :: Python
Classifier: Framework :: Odoo
Classifier: License :: OSI Approved :: GNU Affero General Public License v3
Requires-Python: >=3.5
Requires-Dist: odoo12-addon-shopinvader
Requires-Dist: odoo (<12.1dev,>=12.0a)
